{
  "id": "api/models",
  "title": "models",
  "description": "TOC",
  "source": "@site/docs/api/models.md",
  "sourceDirName": "api",
  "slug": "/api/models",
  "permalink": "/docs/api/models",
  "draft": false,
  "unlisted": false,
  "tags": [],
  "version": "current",
  "sidebarPosition": 3,
  "frontMatter": {
    "title": "models",
    "sidebar_position": 3
  },
  "sidebar": "tutorialSidebar",
  "previous": {
    "title": "generate",
    "permalink": "/docs/api/generate"
  },
  "next": {
    "title": "parse",
    "permalink": "/docs/api/parse"
  }
}
